Logger/__init__.py
Logger/discord.py
Logger/fileLogger.py
Logger/logger.py
Logger/telegram.py
Logger_Zuj3brusu-2.0.dist-info/LICENSE
Logger_Zuj3brusu-2.0.dist-info/METADATA
Logger_Zuj3brusu-2.0.dist-info/WHEEL
Logger_Zuj3brusu-2.0.dist-info/top_level.txt
Logger_Zuj3brusu-2.0.dist-info/RECORD
