Metadata-Version: 2.1
Name: Logger-Zuj3brusu
Version: 2.0
Summary: Create logs on Discord, Telegram or a local file
Home-page: https://github.com/Zuj3brusu/Logger
Author: Zuj3brusu
License: UNKNOWN
Platform: UNKNOWN
Classifier: Programming Language :: Python :: 3
Classifier: License :: OSI Approved :: GNU General Public License v3 (GPLv3)
Classifier: Operating System :: OS Independent
Requires-Python: >=3.6
